Cong0Dao1HyperledgerFabricKaifaJingyao/README.md
Cong0Dao1HyperledgerFabricKaifaJingyao/__init__.py
Cong0Dao1HyperledgerFabricKaifaJingyao/__main__.py
Cong0Dao1HyperledgerFabricKaifaJingyao/file.epub
Cong0Dao1HyperledgerFabricKaifaJingyao/index.html
Cong0Dao1HyperledgerFabricKaifaJingyao/css/__init__.py
Cong0Dao1HyperledgerFabricKaifaJingyao/css/annotations.css
Cong0Dao1HyperledgerFabricKaifaJingyao/css/main.css
Cong0Dao1HyperledgerFabricKaifaJingyao/css/normalize.css
Cong0Dao1HyperledgerFabricKaifaJingyao/css/popup.css
Cong0Dao1HyperledgerFabricKaifaJingyao/font/__init__.py
Cong0Dao1HyperledgerFabricKaifaJingyao/font/fontello.eot
Cong0Dao1HyperledgerFabricKaifaJingyao/font/fontello.svg
Cong0Dao1HyperledgerFabricKaifaJingyao/font/fontello.ttf
Cong0Dao1HyperledgerFabricKaifaJingyao/font/fontello.woff
Cong0Dao1HyperledgerFabricKaifaJingyao/img/__init__.py
Cong0Dao1HyperledgerFabricKaifaJingyao/img/annotator-glyph-sprite.png
Cong0Dao1HyperledgerFabricKaifaJingyao/img/annotator-icon-sprite.png
Cong0Dao1HyperledgerFabricKaifaJingyao/img/apple-touch-icon.png
Cong0Dao1HyperledgerFabricKaifaJingyao/img/cancelfullscreen.png
Cong0Dao1HyperledgerFabricKaifaJingyao/img/close.png
Cong0Dao1HyperledgerFabricKaifaJingyao/img/fullscreen.png
Cong0Dao1HyperledgerFabricKaifaJingyao/img/loader.gif
Cong0Dao1HyperledgerFabricKaifaJingyao/img/menu-icon.png
Cong0Dao1HyperledgerFabricKaifaJingyao/img/save.png
Cong0Dao1HyperledgerFabricKaifaJingyao/img/saved.png
Cong0Dao1HyperledgerFabricKaifaJingyao/img/settings-s.png
Cong0Dao1HyperledgerFabricKaifaJingyao/img/settings.png
Cong0Dao1HyperledgerFabricKaifaJingyao/img/star.png
Cong0Dao1HyperledgerFabricKaifaJingyao/js/__init__.py
Cong0Dao1HyperledgerFabricKaifaJingyao/js/epub.js
Cong0Dao1HyperledgerFabricKaifaJingyao/js/epub.min.js
Cong0Dao1HyperledgerFabricKaifaJingyao/js/epub.min.map
Cong0Dao1HyperledgerFabricKaifaJingyao/js/hooks.min.js
Cong0Dao1HyperledgerFabricKaifaJingyao/js/hooks.min.map
cong_0_dao_1_hyperledger_fabric_kaifa_jingyao-2024.3.5.0.dist-info/METADATA
cong_0_dao_1_hyperledger_fabric_kaifa_jingyao-2024.3.5.0.dist-info/WHEEL
cong_0_dao_1_hyperledger_fabric_kaifa_jingyao-2024.3.5.0.dist-info/entry_points.txt
cong_0_dao_1_hyperledger_fabric_kaifa_jingyao-2024.3.5.0.dist-info/top_level.txt
cong_0_dao_1_hyperledger_fabric_kaifa_jingyao-2024.3.5.0.dist-info/RECORD
